nodeconnector/__init__.py
nodeconnector/nodeconnector.py
nodeconnector-1.0.5.dist-info/METADATA
nodeconnector-1.0.5.dist-info/RECORD
nodeconnector-1.0.5.dist-info/WHEEL
nodeconnector-1.0.5.dist-info/top_level.txt
