Metadata-Version: 2.1
Name: nodeconnector
Version: 1.0.5
Summary: Python connector module for Node.JS applications
Home-page: https://github.com/cristidbr/nodeconnector
Author: Cristian Dobre
Author-email: cristian.dobre@hbfsrobotics.com
License: MIT
Platform: UNKNOWN
Requires-Dist: pyzmq
